MANIFEST.in
readme.txt
setup.py
greet/__init__.py
say_hi.egg-info/PKG-INFO
say_hi.egg-info/SOURCES.txt
say_hi.egg-info/dependency_links.txt
say_hi.egg-info/top_level.txt