Metadata-Version: 1.0
Name: say-hi
Version: 0.0.4
Summary: It wishes the person
Home-page: UNKNOWN
Author: Balaji Betadur
Author-email: balajibetadur@gmail.com
License: UNKNOWN
Keywords: say hi
Platform: UNKNOWN
